color_bucket_logger/__init__.py
color_bucket_logger/formatter.py
color_bucket_logger/mapper.py
color_bucket_logger/styles.py
color_bucket_logger/term_colors.py
color_bucket_logger/term_mapper.py
color_bucket_logger-0.2.0.dist-info/AUTHORS.rst
color_bucket_logger-0.2.0.dist-info/LICENSE
color_bucket_logger-0.2.0.dist-info/METADATA
color_bucket_logger-0.2.0.dist-info/WHEEL
color_bucket_logger-0.2.0.dist-info/top_level.txt
color_bucket_logger-0.2.0.dist-info/RECORD
