Metadata-Version: 2.1
Name: color-bucket-logger
Version: 0.2.0
Summary: Logging Formatter for colorizing logs per thread, process, logger name, or any record attribute
Home-page: https://github.com/alikins/color_bucket_logger
Author: Adrian Likins
Author-email: adrian@likins.com
License: MIT license
Keywords: color_bucket_logger
Platform: UNKNOWN
Classifier: Development Status :: 2 - Pre-Alpha
Classifier: Intended Audience :: Developers
Classifier: License :: OSI Approved :: MIT License
Classifier: Natural Language :: English
Classifier: Programming Language :: Python :: 2
Classifier: Programming Language :: Python :: 2.6
Classifier: Programming Language :: Python :: 2.7
Classifier: Programming Language :: Python :: 3
Classifier: Programming Language :: Python :: 3.3
Classifier: Programming Language :: Python :: 3.4
Classifier: Programming Language :: Python :: 3.5
